hip/__init__.py
hip/_hip_helpers.cpython-38-x86_64-linux-gnu.so
hip/_hip_helpers.pxd
hip/_hip_helpers.pyx
hip/_hiprtc_helpers.cpython-38-x86_64-linux-gnu.so
hip/_hiprtc_helpers.pxd
hip/_hiprtc_helpers.pyx
hip/_version.py
hip/chip.cpython-38-x86_64-linux-gnu.so
hip/chip.pxd
hip/chip.pyx
hip/chipblas.cpython-38-x86_64-linux-gnu.so
hip/chipblas.pxd
hip/chipblas.pyx
hip/chipfft.cpython-38-x86_64-linux-gnu.so
hip/chipfft.pxd
hip/chipfft.pyx
hip/chiprand.cpython-38-x86_64-linux-gnu.so
hip/chiprand.pxd
hip/chiprand.pyx
hip/chiprtc.cpython-38-x86_64-linux-gnu.so
hip/chiprtc.pxd
hip/chiprtc.pyx
hip/chipsolver.cpython-38-x86_64-linux-gnu.so
hip/chipsolver.pxd
hip/chipsolver.pyx
hip/chipsparse.cpython-38-x86_64-linux-gnu.so
hip/chipsparse.pxd
hip/chipsparse.pyx
hip/crccl.cpython-38-x86_64-linux-gnu.so
hip/crccl.pxd
hip/crccl.pyx
hip/croctx.cpython-38-x86_64-linux-gnu.so
hip/croctx.pxd
hip/croctx.pyx
hip/hip.cpython-38-x86_64-linux-gnu.so
hip/hip.pxd
hip/hip.pyx
hip/hipblas.cpython-38-x86_64-linux-gnu.so
hip/hipblas.pxd
hip/hipblas.pyx
hip/hipfft.cpython-38-x86_64-linux-gnu.so
hip/hipfft.pxd
hip/hipfft.pyx
hip/hiprand.cpython-38-x86_64-linux-gnu.so
hip/hiprand.pxd
hip/hiprand.pyx
hip/hiprtc.cpython-38-x86_64-linux-gnu.so
hip/hiprtc.pxd
hip/hiprtc.pyx
hip/hiprtc_pyext.py
hip/hipsolver.cpython-38-x86_64-linux-gnu.so
hip/hipsolver.pxd
hip/hipsolver.pyx
hip/hipsparse.cpython-38-x86_64-linux-gnu.so
hip/hipsparse.pxd
hip/hipsparse.pyx
hip/rccl.cpython-38-x86_64-linux-gnu.so
hip/rccl.pxd
hip/rccl.pyx
hip/roctx.cpython-38-x86_64-linux-gnu.so
hip/roctx.pxd
hip/roctx.pyx
hip/_util/__init__.py
hip/_util/posixloader.cpython-38-x86_64-linux-gnu.so
hip/_util/posixloader.pxd
hip/_util/posixloader.pyx
hip/_util/types.cpython-38-x86_64-linux-gnu.so
hip/_util/types.pxd
hip/_util/types.pyx
hip_python-6.3.3.540.31.dist-info/LICENSE
hip_python-6.3.3.540.31.dist-info/METADATA
hip_python-6.3.3.540.31.dist-info/WHEEL
hip_python-6.3.3.540.31.dist-info/top_level.txt
hip_python-6.3.3.540.31.dist-info/RECORD
