Metadata-Version: 2.1
Name: hip-python-fork
Version: 6.3.3.540.31.1
Summary: Python and Cython bindings for HIP
Home-page: https://github.com/ROCmSoftwarePlatform/hip-python
Author: Advanced Micro Devices, Inc.
Author-email: hip-python.maintainer@amd.com
License: MIT
Platform: UNKNOWN
Classifier: Intended Audience :: Developers
Classifier: Topic :: Scientific/Engineering
Classifier: Topic :: Software Development :: Libraries
Classifier: Environment :: GPU
Classifier: Programming Language :: Python :: 3.7
Classifier: Programming Language :: Cython
Classifier: License :: OSI Approved :: MIT License
Classifier: Development Status :: 2 - Pre-Alpha
Requires-Python: <4,>=3.7
